robloxidesync/__init__.py
robloxidesync/sync.py
roblox_dev_sync-1.0.0.dist-info/METADATA
roblox_dev_sync-1.0.0.dist-info/WHEEL
roblox_dev_sync-1.0.0.dist-info/entry_points.txt
roblox_dev_sync-1.0.0.dist-info/top_level.txt
roblox_dev_sync-1.0.0.dist-info/RECORD
